torrentcli/__init__.py
torrentcli/__main__.py
torrentcli/aria2c/__init__.py
torrentcli/aria2c/wrapper.py
torrentcli/cli.py
torrentcli/config.py
torrentcli/db/__init__.py
torrentcli/db/queries.py
torrentcli/db/schema.py
torrentcli/engine.py
torrentcli/models.py
torrentcli/repl.py
torrentcli/trackers/__init__.py
torrentcli/trackers/manager.py
torrentcli/trackers/sources.py
torrentcli/trackers/udp.py
torrentcli/tui/__init__.py
torrentcli/tui/animations.py
torrentcli/tui/layouts.py
torrentcli/tui/renderer.py
torrentcli/tui/theme.py
torrentcli/utils/__init__.py
torrentcli/utils/bencode.py
torrentcli/utils/formatters.py
torrentcli/utils/health.py
torrentcli_pro-2.0.12.dist-info/METADATA
torrentcli_pro-2.0.12.dist-info/WHEEL
torrentcli_pro-2.0.12.dist-info/entry_points.txt
torrentcli_pro-2.0.12.dist-info/licenses/LICENSE
torrentcli_pro-2.0.12.dist-info/RECORD
