Metadata-Version: 2.4
Name: torrentcli-pro
Version: 2.0.12
Summary: Hardcore terminal torrent client with cyberpunk aesthetics, optimized for rare torrents
License: MIT
License-File: LICENSE
Keywords: torrent,cli,aria2,download,bittorrent,tracker,terminal,tui
Author: TorrentCLI Contributors
Requires-Python: >=3.9,<4.0
Classifier: Development Status :: 4 - Beta
Classifier: Environment :: Console
Classifier: Intended Audience :: End Users/Desktop
Classifier: License :: OSI Approved :: MIT License
Classifier: Operating System :: MacOS
Classifier: Operating System :: POSIX :: Linux
Classifier: Programming Language :: Python :: 3
Classifier: Programming Language :: Python :: 3.9
Classifier: Programming Language :: Python :: 3.10
Classifier: Programming Language :: Python :: 3.11
Classifier: Programming Language :: Python :: 3.12
Classifier: Programming Language :: Python :: 3.13
Classifier: Programming Language :: Python :: 3.14
Classifier: Topic :: Communications :: File Sharing
Classifier: Topic :: Internet
Requires-Dist: click (>=8.1.7,<9.0.0)
Requires-Dist: httpx (>=0.27.0,<0.28.0)
Requires-Dist: rich (>=13.7.0,<14.0.0)
Requires-Dist: tomli (>=2.0.1,<3.0.0) ; python_version < "3.11"
Requires-Dist: tomli-w (>=1.0.0,<2.0.0)
Project-URL: Homepage, https://github.com/torrentcli/torrentcli-pro
Project-URL: Repository, https://github.com/torrentcli/torrentcli-pro
